expbase/__init__.py
expbase/base_config.py
expbase/evaluation_executor.py
expbase/experiment.py
expbase/training_executor.py
expbase/util/__init__.py
expbase/util/printing_tools.py
expbase/util/table.py
expbase/util/timer.py
expbase-0.1.0.data/data/LICENSE
expbase-0.1.0.data/data/README.md
expbase-0.1.0.dist-info/LICENSE
expbase-0.1.0.dist-info/METADATA
expbase-0.1.0.dist-info/WHEEL
expbase-0.1.0.dist-info/top_level.txt
expbase-0.1.0.dist-info/RECORD
