Metadata-Version: 2.1
Name: expbase
Version: 0.1.0
Summary: A Python framework that implements a commonly used boilerplate for machine learning experiments.
Home-page: https://github.com/phohenecker/exp-base
Author: Patrick Hohenecker
Author-email: mail@paho.at
License: BSD-2-Clause
Platform: UNKNOWN
Classifier: Programming Language :: Python :: 3.7
Classifier: Programming Language :: Python :: 3.8
Requires-Python: >=3.7
Requires-Dist: argmagiq (>=0.1.0)
Requires-Dist: insanity (>=2017.1)
Requires-Dist: streamtologger (>=2017.1)
